iopE_sys/__init__.py
iopE_sys-1.0.0.dist-info/METADATA
iopE_sys-1.0.0.dist-info/WHEEL
iopE_sys-1.0.0.dist-info/top_level.txt
iopE_sys-1.0.0.dist-info/RECORD
