Metadata-Version: 2.1
Name: iopE-sys
Version: 1.0.0
Summary: iopE_sys
Home-page: UNKNOWN
Author: GigaAlex
Author-email: nick.faltermeier@gmx.de
License: UNKNOWN
Keywords: python
Platform: UNKNOWN
Classifier: Operating System :: Microsoft :: Windows
